debugged
