Metadata-Version: 1.0
Name: debugged
Version: 0.5
Summary: A developer tool to prepare for and respond to unexpected problems.
Home-page: https://github.com/RokkinCat/debugged-python
Author: Nick Gartmann
Author-email: nick@rokkincat.com
License: BSD
Platform: any
Classifier: Intended Audience :: Developers
Classifier: Operating System :: OS Independent
Classifier: Programming Language :: Python
